geometool/__init__.py
geometool/geometry_tool.py
geometool/test_geometry_tool.py
geometool/utils.py
geometool-0.1.2.dist-info/LICENSE
geometool-0.1.2.dist-info/METADATA
geometool-0.1.2.dist-info/WHEEL
geometool-0.1.2.dist-info/top_level.txt
geometool-0.1.2.dist-info/RECORD
