Metadata-Version: 2.1
Name: geometool
Version: 0.1.2
Summary: A Geometric Shape Calculator Tool
Home-page: https://github.com/K4speeer/Geometry_Tool
Author: Idris Taha
Author-email: dri.taha24@gmail.com
Classifier: Programming Language :: Python :: 3
Classifier: License :: OSI Approved :: MIT License
Classifier: Operating System :: OS Independent
License-File: LICENSE
